[
  {
    "id": "b32883ed-4b06-4187-8391-d3056ce2ee5e",
    "diagnosis": "Positive",
    "age": 45,
    "gender": "male",
    "blood_pressure_systolic": 113,
    "glucose": 296.15,
    "hba1c": 15.1,
    "bmi": 40.31,
    "blood_pressure_diastolic": 71
  },
  {
    "id": "3bcee0c5-6a7f-4cda-bad8-b5e59116ac0d",
    "diagnosis": "Negative",
    "age": 64,
    "gender": "male",
    "blood_pressure_systolic": 119,
    "glucose": 250.3,
    "hba1c": 10.39,
    "bmi": 35.14,
    "blood_pressure_diastolic": 75
  },
  {
    "id": "6576d7d0-3a8f-4a2d-8694-b41e6b1c4afd",
    "diagnosis": "Negative",
    "age": 43,
    "gender": "male",
    "blood_pressure_systolic": 92,
    "glucose": 272.03,
    "hba1c": 12.15,
    "bmi": 25.81,
    "blood_pressure_diastolic": 66
  },
  {
    "id": "26bbd07f-b739-4b74-94ef-132c0f32773b",
    "diagnosis": "Positive",
    "age": 56,
    "gender": "female",
    "blood_pressure_systolic": 114,
    "glucose": 389.83,
    "hba1c": 15.1,
    "bmi": 32.53,
    "blood_pressure_diastolic": 83
  },
  {
    "id": "97737efa-00c3-4cb2-8928-51713f3f961d",
    "diagnosis": "Negative",
    "age": 43,
    "gender": "male",
    "blood_pressure_systolic": 91,
    "glucose": 419.75,
    "hba1c": 15.4,
    "bmi": 26.19,
    "blood_pressure_diastolic": 78
  },
  {
    "id": "e8556f9b-b638-4429-9aee-e1a0eb9f12d9",
    "diagnosis": "Positive",
    "age": 61,
    "gender": "other",
    "blood_pressure_systolic": 118,
    "glucose": 354.14,
    "hba1c": 15.1,
    "bmi": 39.68,
    "blood_pressure_diastolic": 118
  },
  {
    "id": "44cf87f5-6a3f-4c30-97db-eed49f887e5a",
    "diagnosis": "Negative",
    "age": 59,
    "gender": "male",
    "blood_pressure_systolic": 161,
    "glucose": 240.72,
    "hba1c": 14.47,
    "bmi": 33.13,
    "blood_pressure_diastolic": 82
  },
  {
    "id": "99eaae7b-10b8-41eb-9cbb-5a6e121d3d4c",
    "diagnosis": "Positive",
    "age": 72,
    "gender": "male",
    "blood_pressure_systolic": 151,
    "glucose": 266.06,
    "hba1c": 15.1,
    "bmi": 44.52,
    "blood_pressure_diastolic": 74
  },
  {
    "id": "8e2f4e74-78da-4c58-b398-b6464c5a4a5b",
    "diagnosis": "Positive",
    "age": 53,
    "gender": "female",
    "blood_pressure_systolic": 174,
    "glucose": 334.69,
    "hba1c": 15.1,
    "bmi": 36.46,
    "blood_pressure_diastolic": 84
  },
  {
    "id": "34ac4dd3-bff5-4186-a181-9c45b2fb64d9",
    "diagnosis": "Positive",
    "age": 87,
    "gender": "other",
    "blood_pressure_systolic": 128,
    "glucose": 258.04,
    "hba1c": 13.56,
    "bmi": 50.81,
    "blood_pressure_diastolic": 78
  },
  {
    "id": "bb057a34-a80c-410a-807c-4dd5067af361",
    "diagnosis": "Negative",
    "age": 47,
    "gender": "male",
    "blood_pressure_systolic": 112,
    "glucose": 269.89,
    "hba1c": 12.53,
    "bmi": 27.85,
    "blood_pressure_diastolic": 70
  },
  {
    "id": "bae92e27-d5e0-42bd-83c3-af24bd352793",
    "diagnosis": "Negative",
    "age": 59,
    "gender": "male",
    "blood_pressure_systolic": 108,
    "glucose": 257.6,
    "hba1c": 15.4,
    "bmi": 33.2,
    "blood_pressure_diastolic": 64
  },
  {
    "id": "b1c5f2bd-4e87-4836-9269-13cd1fd584e7",
    "diagnosis": "Positive",
    "age": 55,
    "gender": "female",
    "blood_pressure_systolic": 113,
    "glucose": 466.25,
    "hba1c": 15.1,
    "bmi": 37.18,
    "blood_pressure_diastolic": 77
  },
  {
    "id": "9bb76d06-e199-4985-9b72-9836299a4080",
    "diagnosis": "Negative",
    "age": 52,
    "gender": "female",
    "blood_pressure_systolic": 151,
    "glucose": 175.43,
    "hba1c": 14.56,
    "bmi": 29.74,
    "blood_pressure_diastolic": 85
  },
  {
    "id": "37d9e1a6-93a5-4efe-998d-a315ba02d5e0",
    "diagnosis": "Positive",
    "age": 71,
    "gender": "male",
    "blood_pressure_systolic": 123,
    "glucose": 357.96,
    "hba1c": 15.1,
    "bmi": 44.11,
    "blood_pressure_diastolic": 84
  },
  {
    "id": "68c9a367-ad91-4167-bc14-c40aaf1e7f4f",
    "diagnosis": "Negative",
    "age": 63,
    "gender": "male",
    "blood_pressure_systolic": 119,
    "glucose": 428.1,
    "hba1c": 15.4,
    "bmi": 28.09,
    "blood_pressure_diastolic": 83
  },
  {
    "id": "99c518e7-7108-40ab-94a1-667f6700b1b1",
    "diagnosis": "Negative",
    "age": 50,
    "gender": "male",
    "blood_pressure_systolic": 90,
    "glucose": 273.57,
    "hba1c": 15.31,
    "bmi": 29.15,
    "blood_pressure_diastolic": 85
  },
  {
    "id": "c318b462-e9d1-4420-973d-0cf4796606be",
    "diagnosis": "Positive",
    "age": 53,
    "gender": "male",
    "blood_pressure_systolic": 174,
    "glucose": 358.6,
    "hba1c": 15.1,
    "bmi": 32.03,
    "blood_pressure_diastolic": 73
  },
  {
    "id": "5e21dcba-2967-4bed-8405-67903a137d4a",
    "diagnosis": "Negative",
    "age": 59,
    "gender": "female",
    "blood_pressure_systolic": 112,
    "glucose": 174.29,
    "hba1c": 9.57,
    "bmi": 32.82,
    "blood_pressure_diastolic": 65
  },
  {
    "id": "a91f7ef3-310a-49e4-b177-f67c76bbdb4c",
    "diagnosis": "Positive",
    "age": 56,
    "gender": "other",
    "blood_pressure_systolic": 141,
    "glucose": 466.25,
    "hba1c": 15.1,
    "bmi": 37.84,
    "blood_pressure_diastolic": 84
  },
  {
    "id": "2f42f92d-2e3d-4ee2-9a78-5be29afcd15b",
    "diagnosis": "Positive",
    "age": 56,
    "gender": "female",
    "blood_pressure_systolic": 141,
    "glucose": 273.09,
    "hba1c": 15.1,
    "bmi": 37.76,
    "blood_pressure_diastolic": 77
  },
  {
    "id": "953a79b2-31c6-409f-94c0-67ce9adc5c9c",
    "diagnosis": "Negative",
    "age": 52,
    "gender": "other",
    "blood_pressure_systolic": 101,
    "glucose": 262.32,
    "hba1c": 13.52,
    "bmi": 30.05,
    "blood_pressure_diastolic": 79
  },
  {
    "id": "5f7c1314-0e9e-4314-92f3-515728ad89ea",
    "diagnosis": "Positive",
    "age": 43,
    "gender": "other",
    "blood_pressure_systolic": 124,
    "glucose": 322.6,
    "hba1c": 15.1,
    "bmi": 32,
    "blood_pressure_diastolic": 83
  },
  {
    "id": "ad64f4eb-b3a1-4fa9-af7e-eb2341688f0e",
    "diagnosis": "Negative",
    "age": 64,
    "gender": "female",
    "blood_pressure_systolic": 157,
    "glucose": 205.86,
    "hba1c": 12.15,
    "bmi": 35.16,
    "blood_pressure_diastolic": 84
  },
  {
    "id": "bd0c2c73-db3a-4373-bd49-8b7146eff8f7",
    "diagnosis": "Negative",
    "age": 45,
    "gender": "female",
    "blood_pressure_systolic": 119,
    "glucose": 179.7,
    "hba1c": 10.45,
    "bmi": 26.87,
    "blood_pressure_diastolic": 85
  },
  {
    "id": "42689d2f-00d4-4e7d-814c-b1825fc1cbfe",
    "diagnosis": "Negative",
    "age": 54,
    "gender": "other",
    "blood_pressure_systolic": 119,
    "glucose": 198.76,
    "hba1c": 10.59,
    "bmi": 30.86,
    "blood_pressure_diastolic": 81
  },
  {
    "id": "f173a97c-d515-4b65-af95-df1b4194d8b8",
    "diagnosis": "Negative",
    "age": 50,
    "gender": "male",
    "blood_pressure_systolic": 91,
    "glucose": 218.63,
    "hba1c": 9.44,
    "bmi": 30.1,
    "blood_pressure_diastolic": 103
  },
  {
    "id": "8179e477-2197-48cf-b60a-3e9753d2fd6f",
    "diagnosis": "Negative",
    "age": 97,
    "gender": "male",
    "blood_pressure_systolic": 109,
    "glucose": 271.07,
    "hba1c": 13.23,
    "bmi": 49.49,
    "blood_pressure_diastolic": 65
  },
  {
    "id": "0b624606-c974-4536-82a4-5da12e62c274",
    "diagnosis": "Negative",
    "age": 46,
    "gender": "male",
    "blood_pressure_systolic": 119,
    "glucose": 175.12,
    "hba1c": 10.79,
    "bmi": 27.38,
    "blood_pressure_diastolic": 70
  },
  {
    "id": "e328f619-7bb8-44b9-9118-4baa4e386edc",
    "diagnosis": "Negative",
    "age": 62,
    "gender": "female",
    "blood_pressure_systolic": 139,
    "glucose": 227.33,
    "hba1c": 11.58,
    "bmi": 34.32,
    "blood_pressure_diastolic": 84
  },
  {
    "id": "03a9c8a1-51ab-4e1b-8b9a-bfd2bdaa8bb6",
    "diagnosis": "Negative",
    "age": 59,
    "gender": "male",
    "blood_pressure_systolic": 119,
    "glucose": 268.05,
    "hba1c": 10.92,
    "bmi": 33.16,
    "blood_pressure_diastolic": 64
  },
  {
    "id": "7e3abded-a14d-4392-a874-b0e72a0d1dd0",
    "diagnosis": "Negative",
    "age": 64,
    "gender": "other",
    "blood_pressure_systolic": 107,
    "glucose": 322.47,
    "hba1c": 13.6,
    "bmi": 35.04,
    "blood_pressure_diastolic": 64
  },
  {
    "id": "90479af3-9954-44d4-acdd-6d1ba4288a32",
    "diagnosis": "Negative",
    "age": 47,
    "gender": "male",
    "blood_pressure_systolic": 91,
    "glucose": 195.58,
    "hba1c": 15.21,
    "bmi": 27.94,
    "blood_pressure_diastolic": 64
  },
  {
    "id": "6c8107fb-d131-4d3a-a1ff-3c4b331575d4",
    "diagnosis": "Negative",
    "age": 63,
    "gender": "male",
    "blood_pressure_systolic": 115,
    "glucose": 262.1,
    "hba1c": 15.4,
    "bmi": 34.62,
    "blood_pressure_diastolic": 95
  },
  {
    "id": "7ba9d263-7c35-4fbe-9533-728a95c7f9fa",
    "diagnosis": "Positive",
    "age": 61,
    "gender": "other",
    "blood_pressure_systolic": 131,
    "glucose": 457.15,
    "hba1c": 15.1,
    "bmi": 39.89,
    "blood_pressure_diastolic": 78
  },
  {
    "id": "a7dacc07-b5b7-4b82-8b2c-104652207691",
    "diagnosis": "Positive",
    "age": 73,
    "gender": "male",
    "blood_pressure_systolic": 138,
    "glucose": 258.2,
    "hba1c": 15.1,
    "bmi": 45.21,
    "blood_pressure_diastolic": 72
  },
  {
    "id": "7cad2090-e929-496b-a5f6-76794a441c6c",
    "diagnosis": "Negative",
    "age": 100,
    "gender": "female",
    "blood_pressure_systolic": 98,
    "glucose": 177.52,
    "hba1c": 8.16,
    "bmi": 51.93,
    "blood_pressure_diastolic": 67
  },
  {
    "id": "9fca77e8-2e20-4c3d-8cba-4b2ec3326333",
    "diagnosis": "Negative",
    "age": 74,
    "gender": "male",
    "blood_pressure_systolic": 91,
    "glucose": 274.56,
    "hba1c": 15.4,
    "bmi": 50.93,
    "blood_pressure_diastolic": 68
  },
  {
    "id": "f4be2d9e-5ef4-43c3-a404-267425c06354",
    "diagnosis": "Negative",
    "age": 72,
    "gender": "male",
    "blood_pressure_systolic": 117,
    "glucose": 174.13,
    "hba1c": 10.89,
    "bmi": 38.69,
    "blood_pressure_diastolic": 78
  },
  {
    "id": "e7d7c6d1-fd07-436d-a04b-9e2e85feb72f",
    "diagnosis": "Negative",
    "age": 64,
    "gender": "other",
    "blood_pressure_systolic": 115,
    "glucose": 172.28,
    "hba1c": 13.97,
    "bmi": 34.76,
    "blood_pressure_diastolic": 64
  },
  {
    "id": "51a3c209-d986-49ea-a952-74caf47a2014",
    "diagnosis": "Positive",
    "age": 45,
    "gender": "other",
    "blood_pressure_systolic": 124,
    "glucose": 326.99,
    "hba1c": 15.1,
    "bmi": 33.1,
    "blood_pressure_diastolic": 82
  },
  {
    "id": "ba5cf6f9-a8c5-42b5-a430-163c1366db7d",
    "diagnosis": "Negative",
    "age": 65,
    "gender": "male",
    "blood_pressure_systolic": 131,
    "glucose": 213.76,
    "hba1c": 9.4,
    "bmi": 35.58,
    "blood_pressure_diastolic": 82
  },
  {
    "id": "eb661719-859b-45d5-8ff3-286fba51cfbc",
    "diagnosis": "Negative",
    "age": 88,
    "gender": "male",
    "blood_pressure_systolic": 116,
    "glucose": 221.75,
    "hba1c": 10.31,
    "bmi": 45.54,
    "blood_pressure_diastolic": 84
  },
  {
    "id": "94a6c5b6-134b-4157-a127-001a492a5f60",
    "diagnosis": "Negative",
    "age": 100,
    "gender": "female",
    "blood_pressure_systolic": 95,
    "glucose": 286.7,
    "hba1c": 13.85,
    "bmi": 50.96,
    "blood_pressure_diastolic": 107
  },
  {
    "id": "ab7c2503-6eb4-4470-b138-8f57bbe844ac",
    "diagnosis": "Positive",
    "age": 64,
    "gender": "other",
    "blood_pressure_systolic": 117,
    "glucose": 351.94,
    "hba1c": 15.1,
    "bmi": 41.18,
    "blood_pressure_diastolic": 84
  },
  {
    "id": "ea96eb10-d2aa-47a2-8b9e-6d8375d8ea94",
    "diagnosis": "Negative",
    "age": 49,
    "gender": "other",
    "blood_pressure_systolic": 93,
    "glucose": 190.47,
    "hba1c": 10.4,
    "bmi": 28.8,
    "blood_pressure_diastolic": 66
  },
  {
    "id": "89d5db01-7285-490e-b263-17b74c5616b9",
    "diagnosis": "Negative",
    "age": 44,
    "gender": "other",
    "blood_pressure_systolic": 117,
    "glucose": 263.94,
    "hba1c": 13.52,
    "bmi": 26.53,
    "blood_pressure_diastolic": 67
  },
  {
    "id": "2456a321-b05b-4299-a3cc-76d7588b956b",
    "diagnosis": "Positive",
    "age": 91,
    "gender": "male",
    "blood_pressure_systolic": 138,
    "glucose": 349.91,
    "hba1c": 15.1,
    "bmi": 52.6,
    "blood_pressure_diastolic": 69
  },
  {
    "id": "0828f536-b148-4044-98ac-0a9f47e4b282",
    "diagnosis": "Negative",
    "age": 45,
    "gender": "male",
    "blood_pressure_systolic": 104,
    "glucose": 175.97,
    "hba1c": 9.83,
    "bmi": 26.76,
    "blood_pressure_diastolic": 64
  },
  {
    "id": "5dc313f4-514b-4127-8932-bea8dfd5d61f",
    "diagnosis": "Negative",
    "age": 63,
    "gender": "other",
    "blood_pressure_systolic": 126,
    "glucose": 397.58,
    "hba1c": 15.4,
    "bmi": 34.58,
    "blood_pressure_diastolic": 85
  }
]